orkes/__init__.py
orkes/agents/__init__.py
orkes/agents/actions.py
orkes/agents/core.py
orkes/graph/__init__.py
orkes/graph/core.py
orkes/graph/runner.py
orkes/graph/schema.py
orkes/graph/unit.py
orkes/graph/utils.py
orkes/services/__init__.py
orkes/services/connections.py
orkes/services/prompts.py
orkes/services/responses.py
orkes-0.5.0.dist-info/METADATA
orkes-0.5.0.dist-info/WHEEL
orkes-0.5.0.dist-info/top_level.txt
orkes-0.5.0.dist-info/RECORD
