Metadata-Version: 2.4
Name: orkes
Version: 0.5.0
Summary: Lightweight multi-agent orchestration framework
Author-email: Hasby Fahrudin <fahrudinhasby12@gmail.com>
License-Expression: MIT
Project-URL: Homepage, https://github.com/hfahrudin/orkes
Requires-Python: >=3.10
Requires-Dist: pydantic>=2.0
